glm_utils/__init__.py
glm_utils/bases.py
glm_utils/postprocessing.py
glm_utils/preprocessing.py
glm_utils-0.5.2.dist-info/LICENSE
glm_utils-0.5.2.dist-info/WHEEL
glm_utils-0.5.2.dist-info/METADATA
glm_utils-0.5.2.dist-info/RECORD
