Metadata-Version: 2.1
Name: glm-utils
Version: 0.5.2
Summary: Utilities for fitting GLMs.
Home-page: https://github.com/postpop/glm_utils
License: UNKNOWN
Author: Jan Clemens, Adrian Palacios, Deniz Yuezak
Author-email: clemensjan@googlemail.com, adrian@email.com, deniz@email.com
Requires-Python: >=3.7
Classifier: License :: OSI Approved :: MIT License
Requires-Dist: numpy
Requires-Dist: scipy
Requires-Dist: scikit-learn
